{
  "map-t11+": {
    "extends": [
      "map-t6+"
    ],
    "background": "200 200 200 255"
  },
  "map-t6+": {
    "extends": [
      "map-t1+"
    ],
    "background": "150 150 150 255"
  },
  "map-t1+": {
    "extends": [
      "map"
    ],
    "background": "100 100 100 219"
  },
  "map-unique": {
    "extends": [
      "map"
    ],
    "background": "130 70 30 255"
  },
  "map-lab": {
    "extends": [
      "map"
    ],
    "text": "0 0 100 255",
    "border": "0 0 100 255",
    "background": "175 175 255 255"
  },
  "map-fragment": {
    "extends": [
      "map-t6+"
    ]
  },
  "map": {
    "text": "0 0 0 255",
    "beam": "White",
    "icon": "2 White Square",
    "sound": "4 300"
  }
}
